.travis.yml
MANIFEST.in
README.md
README.pypi
setup.py
Orange3_DK.egg-info/PKG-INFO
Orange3_DK.egg-info/SOURCES.txt
Orange3_DK.egg-info/dependency_links.txt
Orange3_DK.egg-info/entry_points.txt
Orange3_DK.egg-info/namespace_packages.txt
Orange3_DK.egg-info/not-zip-safe
Orange3_DK.egg-info/requires.txt
Orange3_DK.egg-info/top_level.txt
orangecontrib/__init__.py
orangecontrib/dynamikontrol/__init__.py
orangecontrib/dynamikontrol/tests/__init__.py
orangecontrib/dynamikontrol/tests/test_example.py
orangecontrib/dynamikontrol/widgets/__init__.py
orangecontrib/dynamikontrol/widgets/angle.py
orangecontrib/dynamikontrol/widgets/case.py
orangecontrib/dynamikontrol/widgets/motor.py
orangecontrib/dynamikontrol/widgets/webcam.py
orangecontrib/dynamikontrol/widgets/icons/WebcamCapture.svg
orangecontrib/dynamikontrol/widgets/icons/angle.png
orangecontrib/dynamikontrol/widgets/icons/case.png
orangecontrib/dynamikontrol/widgets/icons/category.svg
orangecontrib/dynamikontrol/widgets/icons/logo.png
orangecontrib/dynamikontrol/widgets/icons/motor.png
orangecontrib/dynamikontrol/widgets/icons/mywidget.svg