Metadata-Version: 2.1
Name: Orange3-DK
Version: 0.4.0
Summary: Add-on containing Orange3 DynamiKontrol widgets
Home-page: https://dk.m47rix.com
Author: The Matrix
Author-email: contact@m47rix.com
License: MIT
Keywords: orange3 add-on,dynamikontrol,motor
Platform: UNKNOWN
